{
  "updated_at": "12/24/2025, 11:35:13 AM ET",
  "items": [
    {
      "id": "ai-2025-12-24-001",
      "title": "Rising Demand for Synchronous Condensers to Enhance Grid Stability",
      "tldr": "Synchronous condensers are increasingly deployed to improve grid inertia and voltage regulation amid higher renewable penetration.",
      "confidence": "High",
      "tags": [
        "grid stability",
        "synchronous condensers",
        "renewables integration",
        "power systems"
      ],
      "published_at": "12/24/2025, 11:35:13 AM ET",
      "url": "/ai/rising-demand-for-synchronous-condensers-to-enhance-grid-stability.html"
    },
    {
      "id": "ai-2025-12-24-002",
      "title": "HVDC Interconnection Projects Accelerate to Support Cross-Border Power Trade",
      "tldr": "High Voltage Direct Current (HVDC) links are expanding globally to enable efficient long-distance power transmission and cross-border energy exchange.",
      "confidence": "High",
      "tags": [
        "HVDC",
        "interconnection",
        "power transmission",
        "renewables"
      ],
      "published_at": "12/24/2025, 11:35:13 AM ET",
      "url": "/ai/hvdc-interconnection-projects-accelerate-to-support-cross-border-power-trade.html"
    },
    {
      "id": "ai-2025-12-24-003",
      "title": "Data Center Energy Consumption Drives Demand for Advanced Transformers",
      "tldr": "Rapid growth in data center capacity is increasing demand for high-efficiency transformers tailored to dynamic load profiles.",
      "confidence": "Medium",
      "tags": [
        "data centers",
        "transformers",
        "energy efficiency",
        "power equipment"
      ],
      "published_at": "12/24/2025, 11:35:13 AM ET",
      "url": "/ai/data-center-energy-consumption-drives-demand-for-advanced-transformers.html"
    },
    {
      "id": "ai-2025-12-24-004",
      "title": "GIS Technology Adoption Expands in Urban HV Substations",
      "tldr": "Gas-Insulated Switchgear (GIS) is increasingly favored in urban high-voltage substations due to space constraints and reliability benefits.",
      "confidence": "High",
      "tags": [
        "GIS",
        "urban substations",
        "HV equipment",
        "grid reliability"
      ],
      "published_at": "12/24/2025, 11:35:13 AM ET",
      "url": "/ai/gis-technology-adoption-expands-in-urban-hv-substations.html"
    },
    {
      "id": "ai-2025-12-24-005",
      "title": "Rare Earth Element Supply Constraints Impact HV Equipment Manufacturing",
      "tldr": "Supply chain limitations for rare earth elements are affecting production timelines and costs for high voltage equipment such as transformers and motors.",
      "confidence": "Medium",
      "tags": [
        "rare earths",
        "supply chain",
        "HV equipment",
        "materials"
      ],
      "published_at": "12/24/2025, 11:35:13 AM ET",
      "url": "/ai/rare-earth-element-supply-constraints-impact-hv-equipment-manufacturing.html"
    },
    {
      "id": "ai-2025-12-24-006",
      "title": "Transformer Digitalization Enhances Predictive Maintenance Capabilities",
      "tldr": "Integration of digital sensors and IoT in transformers enables real-time condition monitoring and predictive maintenance, reducing downtime and costs.",
      "confidence": "High",
      "tags": [
        "transformers",
        "digitalization",
        "predictive maintenance",
        "IoT"
      ],
      "published_at": "12/24/2025, 11:35:13 AM ET",
      "url": "/ai/transformer-digitalization-enhances-predictive-maintenance-capabilities.html"
    },
    {
      "id": "ai-2025-12-24-007",
      "title": "Grid Stability Challenges Increase with High Renewable Penetration",
      "tldr": "As renewable energy sources reach higher penetration levels, grid operators face increased challenges in maintaining frequency and voltage stability.",
      "confidence": "High",
      "tags": [
        "grid stability",
        "renewables",
        "frequency control",
        "power systems"
      ],
      "published_at": "12/24/2025, 11:35:13 AM ET",
      "url": "/ai/grid-stability-challenges-increase-with-high-renewable-penetration.html"
    },
    {
      "id": "ai-2025-12-24-008",
      "title": "Data Center Operators Increase Focus on Grid Interconnection Resilience",
      "tldr": "Data center operators are prioritizing resilient grid interconnections to ensure uninterrupted power supply amid increasing cyber and physical threats.",
      "confidence": "Medium",
      "tags": [
        "data centers",
        "grid resilience",
        "interconnection",
        "critical infrastructure"
      ],
      "published_at": "12/24/2025, 11:35:13 AM ET",
      "url": "/ai/data-center-operators-increase-focus-on-grid-interconnection-resilience.html"
    },
    {
      "id": "ai-2025-12-24-009",
      "title": "Advances in HV Equipment Insulation Materials Improve Reliability",
      "tldr": "New insulation materials for high voltage equipment are enhancing dielectric strength and thermal performance, leading to improved reliability and lifespan.",
      "confidence": "Medium",
      "tags": [
        "HV equipment",
        "insulation materials",
        "reliability",
        "innovation"
      ],
      "published_at": "12/24/2025, 11:35:13 AM ET",
      "url": "/ai/advances-in-hv-equipment-insulation-materials-improve-reliability.html"
    },
    {
      "id": "ai-2025-12-24-010",
      "title": "Interconnection Queue Backlogs Delay Renewable Project Integration",
      "tldr": "Significant backlogs in interconnection queues are delaying the integration of new renewable energy projects into transmission grids.",
      "confidence": "High",
      "tags": [
        "interconnection",
        "renewables",
        "grid planning",
        "transmission"
      ],
      "published_at": "12/24/2025, 11:35:13 AM ET",
      "url": "/ai/interconnection-queue-backlogs-delay-renewable-project-integration.html"
    }
  ]
}
