{
  "generated_at": "2025-10-04T18:35:11.963215+00:00",
  "articles": [
    {
      "id": "56ca8a",
      "title": "GE Vernova Inc",
      "link": "http://www.bing.com/news/apiclick.aspx?ref=FexRss&aid=&tid=68e168bc90e1403f839e310cf3501d73&url=https%3a%2f%2fwww.reuters.com%2fcompany%2fge-vernova-inc%2f&c=16576099895714596541&mkt=en-us",
      "date": "Wed, 10 Sep 2025 17:00:00 GMT",
      "summary": "Zelenskiy woos US businesses, seeks to grow Ukraine's drone industry President Volodymyr Zelenskiy outlined Ukraine's plans to boost drone exports and expand tech partnerships as he met the top ...",
      "topic": "GE Vernova energy site:reuters.com",
      "image": ""
    },
    {
      "id": "b53322",
      "title": "Exclusive: Bezos-backed renewables alliance targets $7.5 billion for developing countries",
      "link": "http://www.bing.com/news/apiclick.aspx?ref=FexRss&aid=&tid=68e168bc90e1403f839e310cf3501d73&url=https%3a%2f%2fwww.reuters.com%2fsustainability%2fcop%2fbezos-backed-renewables-alliance-targets-75-bln-developing-countries-2025-09-22%2f&c=7953596385328955534&mkt=en-us",
      "date": "Mon, 22 Sep 2025 10:22:00 GMT",
      "summary": "An alliance that installs renewable energy in developing countries wants to invest around $7.5 billion during its next five-year plan, executives told Reuters, and is seeking more philanthropic ...",
      "topic": "GE Vernova energy site:reuters.com",
      "image": ""
    },
    {
      "id": "2cec42",
      "title": "Sumit Saha",
      "link": "http://www.bing.com/news/apiclick.aspx?ref=FexRss&aid=&tid=68e168bc90e1403f839e310cf3501d73&url=https%3a%2f%2fwww.reuters.com%2fauthors%2fsumit-saha%2f&c=10258669570385535543&mkt=en-us",
      "date": "Thu, 11 Sep 2025 17:00:00 GMT",
      "summary": "Trump's energy pivot accelerates US solar and wind power mergers, asset sales The Trump administration's rapid retreat from renewable energy has kicked off consolidation and asset sales among smaller ...",
      "topic": "GE Vernova energy site:reuters.com",
      "image": ""
    },
    {
      "id": "fec275",
      "title": "Vallari Srivastava",
      "link": "http://www.bing.com/news/apiclick.aspx?ref=FexRss&aid=&tid=68e168bc90e1403f839e310cf3501d73&url=https%3a%2f%2fwww.reuters.com%2fauthors%2fvallari-srivastava%2f&c=5142200985043698307&mkt=en-us",
      "date": "Sun, 28 Sep 2025 17:00:00 GMT",
      "summary": "Corteva to split seeds, pesticide units into separate listed companies Corteva said on Wednesday it would separate its seed and pesticide businesses into separate listed companies, as the ...",
      "topic": "GE Vernova energy site:reuters.com",
      "image": ""
    },
    {
      "id": "0089e0",
      "title": "Katha Kalia",
      "link": "http://www.bing.com/news/apiclick.aspx?ref=FexRss&aid=&tid=68e168bc90e1403f839e310cf3501d73&url=https%3a%2f%2fwww.reuters.com%2fauthors%2fkatha-kalia%2f&c=5628901740230538605&mkt=en-us",
      "date": "Tue, 26 Aug 2025 17:00:00 GMT",
      "summary": "Canada's Imperial Oil to cut 20% of workforce and largely exit Calgary Canada's Imperial Oil said on Monday it would cut its workforce by about 20% by the end of 2027, part of a major restructuring ...",
      "topic": "GE Vernova energy site:reuters.com",
      "image": ""
    },
    {
      "id": "3929c1",
      "title": "Sweden looks at compensation law to reduce risk in nuclear expansion",
      "link": "http://www.bing.com/news/apiclick.aspx?ref=FexRss&aid=&tid=68e168bc90e1403f839e310cf3501d73&url=https%3a%2f%2fwww.reuters.com%2fsustainability%2fboards-policy-regulation%2fsweden-looks-compensation-law-reduce-risk-nuclear-expansion-2025-10-02%2f&c=4093689096756739572&mkt=en-us",
      "date": "Thu, 02 Oct 2025 00:31:00 GMT",
      "summary": "Sweden's right-wing government said on Thursday it would look at ways to put in place a law that would compensate nuclear power owners and developers if a future administration decided to close ...",
      "topic": "GE Vernova energy site:reuters.com",
      "image": ""
    },
    {
      "id": "62a140",
      "title": "Zelenskiy woos US businesses, seeks to grow Ukraine's drone industry",
      "link": "http://www.bing.com/news/apiclick.aspx?ref=FexRss&aid=&tid=68e168bc90e1403f839e310cf3501d73&url=https%3a%2f%2fwww.reuters.com%2fbusiness%2fzelenskiy-woos-us-businesses-seeks-grow-ukraines-drone-industry-2025-09-25%2f&c=12098846128397005316&mkt=en-us",
      "date": "Thu, 25 Sep 2025 08:00:00 GMT",
      "summary": "Ukraine to boost drone exports and tech partnerships Zelenskiy meets top U.S. business leaders for investment talks Ukraine's drone industry grows amid war KYIV, Sept 25 (Reuters) - President ...",
      "topic": "GE Vernova energy site:reuters.com",
      "image": ""
    },
    {
      "id": "eab921",
      "title": "Trump's energy pivot accelerates US solar and wind power mergers, asset sales",
      "link": "http://www.bing.com/news/apiclick.aspx?ref=FexRss&aid=&tid=68e168bc90e1403f839e310cf3501d73&url=https%3a%2f%2fwww.reuters.com%2fsustainability%2fclimate-energy%2ftrumps-energy-pivot-accelerates-us-solar-wind-power-mergers-asset-sales-2025-09-26%2f&c=13507610655778882360&mkt=en-us",
      "date": "Fri, 26 Sep 2025 10:37:00 GMT",
      "summary": "Sept 26 (Reuters) - The Trump administration's rapid retreat from renewable energy has kicked off consolidation and asset sales among smaller U.S. solar and wind power companies as they scramble to ...",
      "topic": "GE Vernova energy site:reuters.com",
      "image": ""
    },
    {
      "id": "7b43cf",
      "title": "Nextera Energy Inc",
      "link": "http://www.bing.com/news/apiclick.aspx?ref=FexRss&aid=&tid=68e168bc90e1403f839e310cf3501d73&url=https%3a%2f%2fwww.reuters.com%2fcompany%2fnextera-energy-inc%2f&c=17967623523590190154&mkt=en-us",
      "date": "Sun, 29 Jun 2025 17:00:00 GMT",
      "summary": "NextEra Energy beat Wall Street estimates for second-quarter adjusted profit on Wednesday, boosted by robust growth in its renewables division amid soaring power demand from AI data centers and ...",
      "topic": "GE Vernova energy site:reuters.com",
      "image": ""
    },
    {
      "id": "265494",
      "title": "Simon Johnson",
      "link": "http://www.bing.com/news/apiclick.aspx?ref=FexRss&aid=&tid=68e168bc90e1403f839e310cf3501d73&url=https%3a%2f%2fwww.reuters.com%2fauthors%2fsimon-johnson%2f&c=9007322098512656865&mkt=en-us",
      "date": "Tue, 19 Aug 2025 17:00:00 GMT",
      "summary": "Swedish, Polish forces simulate defence of Gotland amid Baltic tensions The Swedish island of Gotland holds the key to control of the Baltic Sea, according to Swedish and Polish officers taking part ...",
      "topic": "GE Vernova energy site:reuters.com",
      "image": ""
    },
    {
      "id": "eca1a0",
      "title": "Cadeler Takes Delivery of First A-Class Vessel and Enters New Strategic Chapter in Offshore Foundations",
      "link": "http://www.bing.com/news/apiclick.aspx?ref=FexRss&aid=&tid=68e168bd51b249e0a8ee78952bb0cc98&url=https%3a%2f%2fwww.businesswire.com%2fnews%2fhome%2f20250925431471%2fen%2fCadeler-Takes-Delivery-of-First-A-Class-Vessel-and-Enters-New-Strategic-Chapter-in-Offshore-Foundations&c=2488381457100253767&mkt=en-us",
      "date": "Wed, 24 Sep 2025 21:22:00 GMT",
      "summary": "COPENHAGEN, Denmark--(BUSINESS WIRE)--Wind Ally becomes the ninth vessel on the water in Cadeler\u2019s growing fleet of next-generation wind installation vessels (WIV). After her scheduled mobilisation, ...",
      "topic": "Siemens Energy site:businesswire.com",
      "image": ""
    },
    {
      "id": "f136bb",
      "title": "Siemens Energy Signs Agreement to Build First-of-its-Kind Waste Heat-to-Power Facility in Canada",
      "link": "http://www.bing.com/news/apiclick.aspx?ref=FexRss&aid=&tid=68e168bd51b249e0a8ee78952bb0cc98&url=https%3a%2f%2fwww.businesswire.com%2fnews%2fhome%2f20210212005363%2fen%2fSiemens-Energy-Signs-Agreement-to-Build-First-of-its-Kind-Waste-Heat-to-Power-Facility-in-Canada&c=13646379274904341191&mkt=en-us",
      "date": "Fri, 12 Feb 2021 02:14:00 GMT",
      "summary": "Enough electricity will be produced to power 10,000+ homes, resulting in an estimated reduction in 44,000 tons per year in greenhouse gas emissions HOUSTON--(BUSINESS WIRE)--Siemens Energy has signed ...",
      "topic": "Siemens Energy site:businesswire.com",
      "image": ""
    },
    {
      "id": "9e3c3e",
      "title": "Siemens Energy to supply world\u2019s first emissions-reducing gas/electric hybrid drive system for an LNG plant",
      "link": "http://www.bing.com/news/apiclick.aspx?ref=FexRss&aid=&tid=68e168bd51b249e0a8ee78952bb0cc98&url=https%3a%2f%2fwww.businesswire.com%2fnews%2fhome%2f20221020005036%2fen%2fSiemens-Energy-to-supply-world%25E2%2580%2599s-first-emissions-reducing-gaselectric-hybrid-drive-system-for-an-LNG-plant&c=9091542149810965536&mkt=en-us",
      "date": "Thu, 20 Oct 2022 02:00:00 GMT",
      "summary": "HOUSTON--(BUSINESS WIRE)--Northeast Energy Center (NEC) and Chart Energy & Chemicals selected Siemens Energy to supply a gas/electric hybrid drive system for NEC\u2019s LNG plant being built in Charlton, ...",
      "topic": "Siemens Energy site:businesswire.com",
      "image": ""
    },
    {
      "id": "32144c",
      "title": "Siemens Energy Donates $250k Through Positive Energy Campaign",
      "link": "http://www.bing.com/news/apiclick.aspx?ref=FexRss&aid=&tid=68e168bd51b249e0a8ee78952bb0cc98&url=https%3a%2f%2fwww.businesswire.com%2fnews%2fhome%2f20210118005074%2fen%2fSiemens-Energy-Donates-250k-Through-Positive-Energy-Campaign&c=5058208885905972093&mkt=en-us",
      "date": "Mon, 18 Jan 2021 00:00:00 GMT",
      "summary": "ORLANDO--(BUSINESS WIRE)--On the occasion of the Martin Luther King holiday, the only federal holiday designated as a day of service, Siemens Energy is pleased to announce the winning charitable ...",
      "topic": "Siemens Energy site:businesswire.com",
      "image": ""
    },
    {
      "id": "fc818e",
      "title": "Siemens Energy to Power the World\u2019s Lowest-Emission LNG Facility",
      "link": "http://www.bing.com/news/apiclick.aspx?ref=FexRss&aid=&tid=68e168bd51b249e0a8ee78952bb0cc98&url=https%3a%2f%2fwww.businesswire.com%2fnews%2fhome%2f20220712005769%2fen%2fSiemens-Energy-to-Power-the-World%25E2%2580%2599s-Lowest-Emission-LNG-Facility&c=18294831107539130246&mkt=en-us",
      "date": "Tue, 12 Jul 2022 02:00:00 GMT",
      "summary": "Woodfibre LNG will be powered by clean, renewable hydroelectric power, reducing its greenhouse gas emissions by more than 80% Siemens Energy will provide motors, variable speed drives, and the main ...",
      "topic": "Siemens Energy site:businesswire.com",
      "image": ""
    },
    {
      "id": "27037c",
      "title": "Siemens Energy to provide hydrogen-capable turbines to back up utility-scale solar installation in Nebraska",
      "link": "http://www.bing.com/news/apiclick.aspx?ref=FexRss&aid=&tid=68e168bd51b249e0a8ee78952bb0cc98&url=https%3a%2f%2fwww.businesswire.com%2fnews%2fhome%2f20210617005599%2fen%2fSiemens-Energy-to-provide-hydrogen-capable-turbines-to-back-up-utility-scale-solar-installation-in-Nebraska&c=16454468973939616515&mkt=en-us",
      "date": "Thu, 17 Jun 2021 03:04:00 GMT",
      "summary": "Reliability of added power generation will help Omaha Public Power District (OPPD) meet the growing energy needs of the community as part of its Power with Purpose initiative Quick-start modern ...",
      "topic": "Siemens Energy site:businesswire.com",
      "image": ""
    },
    {
      "id": "08fd6c",
      "title": "Siemens Energy Installs World\u2019s First Leased Rapid Response Transformers Allowing a Large Generating Facility to Return to Service",
      "link": "http://www.bing.com/news/apiclick.aspx?ref=FexRss&aid=&tid=68e168bd51b249e0a8ee78952bb0cc98&url=https%3a%2f%2fwww.businesswire.com%2fnews%2fhome%2f20211011005079%2fen%2fSiemens-Energy-Installs-World%25E2%2580%2599s-First-Leased-Rapid-Response-Transformers-Allowing-a-Large-Generating-Facility-to-Return-to-Service&c=204062260964970818&mkt=en-us",
      "date": "Mon, 11 Oct 2021 01:00:00 GMT",
      "summary": "Siemens Energy\u2019s on-demand mobile resistance transformer allows equipment to be leased out and deployed rapidly to maximize grid resilience while mitigating the impacts of long-term outages or for ...",
      "topic": "Siemens Energy site:businesswire.com",
      "image": ""
    },
    {
      "id": "897d32",
      "title": "Siemens Energy Commissions Low-Emissions Compressor Trains for Canadian Gas Plant",
      "link": "http://www.bing.com/news/apiclick.aspx?ref=FexRss&aid=&tid=68e168bd51b249e0a8ee78952bb0cc98&url=https%3a%2f%2fwww.businesswire.com%2fnews%2fhome%2f20210129005052%2fen%2fSiemens-Energy-Commissions-Low-Emissions-Compressor-Trains-for-Canadian-Gas-Plant&c=14832146159002345112&mkt=en-us",
      "date": "Fri, 29 Jan 2021 01:00:00 GMT",
      "summary": "Commissioning of one feed and one sales gas train and one refrigeration compression train complete for the Pipestone Processing Facility. Siemens Energy will provide tailored maintenance services to ...",
      "topic": "Siemens Energy site:businesswire.com",
      "image": ""
    },
    {
      "id": "da3b90",
      "title": "Siemens Energy wins its first black-start battery storage project for power generation in the U.S.",
      "link": "http://www.bing.com/news/apiclick.aspx?ref=FexRss&aid=&tid=68e168bd51b249e0a8ee78952bb0cc98&url=https%3a%2f%2fwww.businesswire.com%2fnews%2fhome%2f20210128005868%2fen%2fSiemens-Energy-wins-its-first-black-start-battery-storage-project-for-power-generation-in-the-U.S.&c=5278504579944711920&mkt=en-us",
      "date": "Thu, 28 Jan 2021 04:00:00 GMT",
      "summary": "ORLANDO, Fla.--(BUSINESS WIRE)--Siemens Energy announced today that it will design, build and commission a black-start system at Clearway\u2019s Marsh Landing Generating Station near Antioch, California ...",
      "topic": "Siemens Energy site:businesswire.com",
      "image": ""
    },
    {
      "id": "00214c",
      "title": "Siemens and U.S. startup LO3 Energy collaborate on blockchain microgrids",
      "link": "http://www.bing.com/news/apiclick.aspx?ref=FexRss&aid=&tid=68e168bd51b249e0a8ee78952bb0cc98&url=https%3a%2f%2fwww.businesswire.com%2fnews%2fhome%2f20161121005686%2fen%2fSiemens-U.S.-startup-LO3-Energy-collaborate-blockchain&c=14734336024456814495&mkt=en-us",
      "date": "Mon, 21 Nov 2016 02:00:00 GMT",
      "summary": "NEW YORK--(BUSINESS WIRE)--Siemens and the New York startup LO3 Energy are collaborating in the field of innovative microgrids. The goal of the collaboration is to jointly develop microgrids that ...",
      "topic": "Siemens Energy site:businesswire.com",
      "image": ""
    },
    {
      "id": "b67a49",
      "title": "Siemens and Macquarie\u2019s Green Investment Group Launch Distributed Energy Venture Calibrant Energy",
      "link": "http://www.bing.com/news/apiclick.aspx?ref=FexRss&aid=&tid=68e168bd51b249e0a8ee78952bb0cc98&url=https%3a%2f%2fwww.businesswire.com%2fnews%2fhome%2f20201005005139%2fen%2fSiemens-and-Macquarie%25E2%2580%2599s-Green-Investment-Group-Launch-Distributed-Energy-Venture-Calibrant-Energy&c=11619638714949803664&mkt=en-us",
      "date": "Mon, 05 Oct 2020 00:30:00 GMT",
      "summary": "NEW YORK & BUFFALO GROVE, Ill.--(BUSINESS WIRE)--Macquarie\u2019s Green Investment Group (GIG), Siemens\u2019 Smart Infrastructure (SI) and Financial Services (SFS) groups today announced the formation of ...",
      "topic": "Siemens Energy site:businesswire.com",
      "image": ""
    },
    {
      "id": "fe3f1d",
      "title": "Air Liquide and Siemens Energy Form a Joint Venture for the European Production of Large-scale Renewable Hydrogen Electrolyzers",
      "link": "http://www.bing.com/news/apiclick.aspx?ref=FexRss&aid=&tid=68e168bd51b249e0a8ee78952bb0cc98&url=https%3a%2f%2fwww.businesswire.com%2fnews%2fhome%2f20220622005789%2fen%2fAir-Liquide-and-Siemens-Energy-Form-a-Joint-Venture-for-the-European-Production-of-Large-scale-Renewable-Hydrogen-Electrolyzers&c=6763324855780441937&mkt=en-us",
      "date": "Wed, 22 Jun 2022 20:43:00 GMT",
      "summary": "PARIS--(BUSINESS WIRE)--Regulatory News: Air Liquide (Paris:AI) and Siemens Energy announce the creation of a joint venture dedicated to the series production of industrial scale renewable hydrogen ...",
      "topic": "Siemens Energy site:businesswire.com",
      "image": ""
    },
    {
      "id": "8fdc98",
      "title": "ABB Endorses Major Smart Grid Research Center at N.C. State University",
      "link": "http://www.bing.com/news/apiclick.aspx?ref=FexRss&aid=&tid=68e168bffe4e42ed8504e062abf4ac2b&url=https%3a%2f%2fwww.tdworld.com%2fhome%2farticle%2f20968042%2fabb-endorses-major-smart-grid-research-center-at-nc-state-university&c=2939783343075660831&mkt=en-us",
      "date": "Tue, 23 Sep 2008 17:00:00 GMT",
      "summary": "ABB to support FREEDM System, following $28.5 million NSF grant, with technology development modernizing the power grid and speeding renewable energy development Washington, DC, Sept. 24, 2008 \u2013- ABB, ...",
      "topic": "ABB grid",
      "image": "https://img.tdworld.com/files/base/ebm/tdworld/image/static/tdworld-logo.png?auto=format,compress&fit=fill&fill=solid&fill-color=&w=1200&h=627"
    },
    {
      "id": "7bf41b",
      "title": "ABB launches new Smart Grid Optimization webinar series",
      "link": "http://www.bing.com/news/apiclick.aspx?ref=FexRss&aid=&tid=68e168bffe4e42ed8504e062abf4ac2b&url=https%3a%2f%2fwww.tdworld.com%2fgrid-innovations%2fsmart-grid%2farticle%2f20967470%2fabb-launches-new-smart-grid-optimization-webinar-series&c=7666728279806157675&mkt=en-us",
      "date": "Wed, 22 Jul 2015 17:00:00 GMT",
      "summary": "Free, interactive online educational series from experts with ABB\u2019s Smart Grid Center of Excellence focuses on \"POWERful insights\" for today's rapidly evolving grid. Raleigh, NC, July 23, 2015 \u2013 ABB, ...",
      "topic": "ABB grid",
      "image": "https://img.tdworld.com/files/base/ebm/tdworld/image/2019/03/tdworld_4785_abb_launches_smart_grid_optimizationwebinar_series20150723.png?auto=format,compress&fit=fill&fill=blur&w=1200&h=630"
    },
    {
      "id": "bc456e",
      "title": "ABB announces first fully integrated smart grid interface for solar power",
      "link": "http://www.bing.com/news/apiclick.aspx?ref=FexRss&aid=&tid=68e168bffe4e42ed8504e062abf4ac2b&url=https%3a%2f%2fwww.pv-magazine.com%2fpress-releases%2fabb-announces-first-fully-integrated-smart-grid-interface-for-solar-power_10008346%2f&c=518437587136255839&mkt=en-us",
      "date": "Tue, 04 Sep 2012 16:59:00 GMT",
      "summary": "ABB, the leading power and automation technology company, will introduce the world s first fully integrated solar power generation plant controller and smart grid interface as part of its Concentrated ...",
      "topic": "ABB grid",
      "image": "https://www.pv-magazine.com/wp-content/themes/pvmagazine/_/img/pv-magazine-logo.png"
    },
    {
      "id": "cf3277",
      "title": "ABB wins $150 million order to grid-connect world\u2019s largest offshore wind farm",
      "link": "http://www.bing.com/news/apiclick.aspx?ref=FexRss&aid=&tid=68e168bffe4e42ed8504e062abf4ac2b&url=https%3a%2f%2fwww.powermag.com%2fpress-releases%2fabb-wins-150-million-order-to-grid-connect-worlds-largest-offshore-wind-farm%2f&c=5779053148193352653&mkt=en-us",
      "date": "Thu, 12 Jul 2018 10:35:00 GMT",
      "summary": "Key technologies and ABB Ability digital solutions will integrate wind energy from Hornsea Project Two to the UK grid, powering more than 1.3 million homes. ABB has won orders worth more than $150 ...",
      "topic": "ABB grid",
      "image": "https://www.powermag.com/wp-content/uploads/2017/09/fc_pwr_030120.jpg"
    },
    {
      "id": "a71c0a",
      "title": "ABB to Invest $110 Million in U.S. to Meet Data Center, Grid Demand",
      "link": "http://www.bing.com/news/apiclick.aspx?ref=FexRss&aid=&tid=68e168bffe4e42ed8504e062abf4ac2b&url=https%3a%2f%2fwww.msn.com%2fen-us%2fmoney%2fmarkets%2fabb-to-invest-110-million-in-us-to-meet-data-center-grid-demand%2far-AA1MEVH5&c=17115456055201602456&mkt=en-us",
      "date": "Tue, 16 Sep 2025 05:53:00 GMT",
      "summary": "The investment covers four manufacturing sites and would allow the company to make its Emax 3 circuit breakers in the U.S.",
      "topic": "ABB grid",
      "image": ""
    },
    {
      "id": "65a01a",
      "title": "ABB's Dr. Matthew Wise and Andressa Ferraz Named Among Future of Field Service's 2025 Stand Out 50 Leaders",
      "link": "http://www.bing.com/news/apiclick.aspx?ref=FexRss&aid=&tid=68e168bffe4e42ed8504e062abf4ac2b&url=https%3a%2f%2ffinance.yahoo.com%2fnews%2fabbs-dr-matthew-wise-andressa-010000922.html&c=843552916364555993&mkt=en-us",
      "date": "Tue, 30 Sep 2025 18:08:00 GMT",
      "summary": "ABB's Dr. Matthew Wise and Andressa Ferraz recognized among Future of Field Service's 2025 Stand Out 50 Leaders.",
      "topic": "ABB grid",
      "image": "https://media.zenfs.com/en/business-wire.com/e8260cb95305d739b01fa217e62242fe"
    },
    {
      "id": "56a3a8",
      "title": "ABB enables world\u2019s first HVDC grid in China",
      "link": "http://www.bing.com/news/apiclick.aspx?ref=FexRss&aid=&tid=68e168bffe4e42ed8504e062abf4ac2b&url=https%3a%2f%2fwww.powermag.com%2fpress-releases%2fabb-enables-worlds-first-hvdc-grid-in-china%2f&c=1138499960264329768&mkt=en-us",
      "date": "Mon, 12 Nov 2018 16:00:00 GMT",
      "summary": "The Zhangbei high-voltage direct current (HVDC) grid in the Beijing-Tianjin-Hebei area of China will enable the integration of remote wind, solar and hydro energy in a transmission ring that ensures ...",
      "topic": "ABB grid",
      "image": "https://www.powermag.com/wp-content/uploads/2017/09/fc_pwr_030120.jpg"
    },
    {
      "id": "7a1063",
      "title": "ABB Acquires KEYMILE\u2019s Communication Networks Business to Strengthen Digital Grid Portfolio and Software Focus",
      "link": "http://www.bing.com/news/apiclick.aspx?ref=FexRss&aid=&tid=68e168bffe4e42ed8504e062abf4ac2b&url=https%3a%2f%2fwww.businesswire.com%2fnews%2fhome%2f20170703005138%2fen%2fABB-Acquires-KEYMILE%25E2%2580%2599s-Communication-Networks-Business-to-Strengthen-Digital-Grid-Portfolio-and-Software-Focus&c=1047230479377681636&mkt=en-us",
      "date": "Sun, 02 Jul 2017 22:00:00 GMT",
      "summary": "Acquisition supports ABB Ability TM offering for mission-critical power grid applications, extending market opportunities ZURICH--(BUSINESS WIRE)--ABB today announced it has agreed to acquire the ...",
      "topic": "ABB grid",
      "image": ""
    },
    {
      "id": "e5e6f1",
      "title": "ABB digital solution to enable power grid in France to get smarter",
      "link": "http://www.bing.com/news/apiclick.aspx?ref=FexRss&aid=&tid=68e168bffe4e42ed8504e062abf4ac2b&url=https%3a%2f%2fwww.pv-magazine.com%2fpress-releases%2fabb-digital-solution-to-enable-power-grid-in-france-to-get-smarter%2f&c=9630879249783135799&mkt=en-us",
      "date": "Tue, 07 Nov 2017 16:00:00 GMT",
      "summary": "ABB has been selected by RTE (R\u00e9seau de transport d\u2019\u00e9lectricit\u00e9) to deploy its ABB Ability Network Manager control system, which will enable operators to monitor and control the grid more efficiently.",
      "topic": "ABB grid",
      "image": "https://www.pv-magazine.com/wp-content/themes/pvmagazine/_/img/pv-magazine-logo.png"
    },
    {
      "id": "39281e",
      "title": "ABB Chief Steps Down After Power-Grid Split Fails to Impress",
      "link": "http://www.bing.com/news/apiclick.aspx?ref=FexRss&aid=&tid=68e168bffe4e42ed8504e062abf4ac2b&url=https%3a%2f%2fwww.industryweek.com%2fleadership%2farticle%2f22027463%2fabb-chief-steps-down-after-power-grid-split-fails-to-impress&c=2912170338274036630&mkt=en-us",
      "date": "Tue, 16 Apr 2019 17:00:00 GMT",
      "summary": "Spiesshofer\u2019s unexpected departure comes after he announced the sale of ABB\u2019s power-grid division to Hitachi Ltd. for about $6.4 billion in December. ABB Ltd. Chief Executive Officer Ulrich ...",
      "topic": "ABB grid",
      "image": "https://img.industryweek.com/files/base/ebm/industryweek/image/2019/04/industryweek_12063_spiesshofer_ulrich_abb.png?auto=format,compress&fit=fill&fill=blur&w=1200&h=630"
    },
    {
      "id": "018fbb",
      "title": "Smart Grid Consolidation Continues: ABB, EnerNoc Both Expand",
      "link": "http://www.bing.com/news/apiclick.aspx?ref=FexRss&aid=&tid=68e168bffe4e42ed8504e062abf4ac2b&url=https%3a%2f%2fwww.fool.com%2finvesting%2fgeneral%2f2010%2f12%2f06%2fsmart-grid-consolidation-continues-abb-enernoc-bot.aspx&c=15634138973784515844&mkt=en-us",
      "date": "Sun, 05 Dec 2010 16:00:00 GMT",
      "summary": "EnerNoc's 9th acquisition and ABB's third in recent months. The shopping season is upon us. ABB (NYSE: ABB), the Swedish/Swiss conglomerate, today announced that it is buying Insert Key Solutions, ...",
      "topic": "ABB grid",
      "image": "https://optimize.foolcdn.com/?url=https%3A%2F%2Fg.foolcdn.com%2Fmisc-assets/jester.png&w=400&op=resize"
    },
    {
      "id": "3c79ec",
      "title": "Mitsubishi secures order for M100S BFG turbine from Chinese steelmaker",
      "link": "http://www.bing.com/news/apiclick.aspx?ref=FexRss&aid=&tid=68e168c5d67846f5821072741e4ab42d&url=https%3a%2f%2fwww.msn.com%2fen-us%2fmoney%2fmarkets%2fmitsubishi-secures-order-for-m100s-bfg-turbine-from-chinese-steelmaker%2far-AA1NGf0z&c=3441020272770434161&mkt=en-us",
      "date": "Wed, 01 Oct 2025 01:38:54 GMT",
      "summary": "M itsubishi Power, a unit of Mitsubishi Heavy Industries, has secured its first order for the newly developed M100S small-to medium-sized gas turbine, designed for use in blast furnace gas (BFG)-fired ...",
      "topic": "Mitsubishi Power",
      "image": ""
    },
    {
      "id": "9391dd",
      "title": "Mitsubishi Electric Power Products, Inc. Celebrates 40 Years of Commitment, Innovation, and Growth",
      "link": "http://www.bing.com/news/apiclick.aspx?ref=FexRss&aid=&tid=68e168c5d67846f5821072741e4ab42d&url=https%3a%2f%2ffinance.yahoo.com%2fnews%2fmitsubishi-electric-power-products-inc-120000964.html&c=14863727193268060651&mkt=en-us",
      "date": "Thu, 25 Sep 2025 05:22:00 GMT",
      "summary": "Mitsubishi Electric Power Products, Inc. (MEPPI), a wholly owned U.S. subsidiary of Mitsubishi Electric Corporation of Japan, proudly celebrates its 40th anniversary today. Founded in 1985, MEPPI has ...",
      "topic": "Mitsubishi Power",
      "image": "https://media.zenfs.com/en/business-wire.com/306662301d306b8ceba3a0eceeb19d34"
    },
    {
      "id": "4d7fa0",
      "title": "Thailand\u2019s Eight-Unit, 5,300-MW Power Project Wins Top Plant Award",
      "link": "http://www.bing.com/news/apiclick.aspx?ref=FexRss&aid=&tid=68e168c5d67846f5821072741e4ab42d&url=https%3a%2f%2fwww.powermag.com%2fthailands-eight-unit-5300-mw-power-project-wins-top-plant-award%2f&c=7082949868774728925&mkt=en-us",
      "date": "Tue, 30 Sep 2025 21:40:00 GMT",
      "summary": "Southeast Asia\u2019s first-ever JAC gas turbines are now supplying power to Thailand\u2019s grid. With efficiency greater than 64%, the eight units deployed\u2014four each at the Sriracha Power Plant in Chonburi ...",
      "topic": "Mitsubishi Power",
      "image": "https://www.powermag.com/wp-content/uploads/2025/10/fig1-chonburi-gtcc-power-plant-thailand-c-bigger.jpg"
    },
    {
      "id": "218fa3",
      "title": "UCF and Mitsubishi Power work together for clean energy",
      "link": "http://www.bing.com/news/apiclick.aspx?ref=FexRss&aid=&tid=68e168c5d67846f5821072741e4ab42d&url=https%3a%2f%2fwww.wftv.com%2fnews%2flocal%2forange-county%2fucf-mitsubishi-power-work-together-clean-energy%2f4I2MYV66HFCGDHOAWZOQGGNQWQ%2f&c=17034663482765001810&mkt=en-us",
      "date": "Sun, 11 Sep 2022 17:34:00 GMT",
      "summary": "ORANGE COUNTY, Fla. \u2014 The University of Central Florida and representatives from Mitsubishi Power met Thursday on campus to address the role of hydrogen in clean energy. This was part of the Hydrogen: ...",
      "topic": "Mitsubishi Power",
      "image": "https://cmg-cmg-tv-10070-prod.cdn.arcpublishing.com/resizer/v2/https%3A%2F%2Fcloudfront-us-east-1.images.arcpublishing.com%2Fcmg%2FXIPTFBYZBVGOTHYQPJLQ7GX5GM.PNG?auth=6f73decc790e66ddea201d91ec63b707af8f8cd61dcc034e58ead05463389418&width=1200&height=630&smart=true"
    },
    {
      "id": "feac08",
      "title": "Mitsubishi Brings Final Unit of 5.3-GW Gas-Fired Thailand Project Online",
      "link": "http://www.bing.com/news/apiclick.aspx?ref=FexRss&aid=&tid=68e168c5d67846f5821072741e4ab42d&url=https%3a%2f%2fwww.powermag.com%2fmitsubishi-brings-final-unit-of-5-3-gw-gas-fired-thailand-project-online%2f&c=3815058741371782215&mkt=en-us",
      "date": "Tue, 08 Oct 2024 17:00:00 GMT",
      "summary": "Mitsubishi Power announced completion of a 5.3-GW natural gas-fired power plant project in Thailand, with the multi-phase installation now fully in commercial operation. The two combined-cycle power ...",
      "topic": "Mitsubishi Power",
      "image": "https://live-powermag.pantheonsite.io/wp-content/uploads/2024/10/rayong-mitsubishi-power-in-thailand-1024x786.png"
    },
    {
      "id": "d5a982",
      "title": "Mitsubishi Power CEO on energy transition and rising data centre demands",
      "link": "http://www.bing.com/news/apiclick.aspx?ref=FexRss&aid=&tid=68e168c5d67846f5821072741e4ab42d&url=https%3a%2f%2fwww.channelnewsasia.com%2fbusiness%2fmitsubishi-power-takao-tsukui-energy-transition-data-centre-5370486&c=1599668419680571751&mkt=en-us",
      "date": "Thu, 25 Sep 2025 18:55:00 GMT",
      "summary": "Takao Tsukui highlighted the challenges and opportunities facing the clean energy technology manufacturing sector amid shifting global dynamics, in an interview with CNA\u2019s Elizabeth Neo.",
      "topic": "Mitsubishi Power",
      "image": "https://dam.mediacorp.sg/image/upload/s--wgK7nFd8--/c_fill,g_auto,h_676,w_1200/fl_relative,g_south_east,l_mediacorp:cna:watermark:2021-08:cna,w_0.1/f_auto,q_auto/v1/mediacorp/cna/image/2025/09/25/mitsubishi_power_takao_tsukui.png?itok=Hx7PiVeX"
    },
    {
      "id": "731751",
      "title": "Mitsubishi Electric\u2019s Railcar Motor System Wins R&D 100 Award",
      "link": "http://www.bing.com/news/apiclick.aspx?ref=FexRss&aid=&tid=68e168c5d67846f5821072741e4ab42d&url=https%3a%2f%2ffinance.yahoo.com%2fnews%2fmitsubishi-electric-railcar-motor-system-030000789.html&c=7686752862095025945&mkt=en-us",
      "date": "Thu, 02 Oct 2025 20:20:00 GMT",
      "summary": "Mitsubishi Electric Corporation (TOKYO: 6503) announced today that its energy- and resource-saving synchronous reluctance motor and inverter traction system (SynTRACS) for railcars has received a 2025 ...",
      "topic": "Mitsubishi Power",
      "image": "https://media.zenfs.com/en/business-wire.com/9b7f557e66b3d2cdecd70026b5e71163"
    },
    {
      "id": "8e1a96",
      "title": "Mitsubishi Power pursues ammonia-fired power generation in Indonesia, Singapore",
      "link": "http://www.bing.com/news/apiclick.aspx?ref=FexRss&aid=&tid=68e168c5d67846f5821072741e4ab42d&url=https%3a%2f%2fwww.power-eng.com%2fgas%2fturbines%2fmitsubishi-power-pursues-ammonia-fired-power-generation-in-indonesia-singapore%2f&c=549028996722906164&mkt=en-us",
      "date": "Thu, 29 Sep 2022 16:59:00 GMT",
      "summary": "Mitsubishi Power and Indonesia\u2019s Institut Teknologi Bandung (ITB) plan to research firing ammonia in gas turbines under a new agreement. Following demonstration testing with Mitsubishi Power\u2019s H-25 ...",
      "topic": "Mitsubishi Power",
      "image": "https://www.power-eng.com/wp-content/uploads/2022/09/ff.png"
    },
    {
      "id": "c8f205",
      "title": "Mitsubishi Power MENA chief on meeting AI-driven energy demand",
      "link": "http://www.bing.com/news/apiclick.aspx?ref=FexRss&aid=&tid=68e168c5d67846f5821072741e4ab42d&url=https%3a%2f%2fgulfbusiness.com%2fmitsubishi-power-mena-chief-on-meeting-ai-driven-energy-demand%2f&c=3646546978797059668&mkt=en-us",
      "date": "Tue, 02 Sep 2025 02:22:00 GMT",
      "summary": "IEA projections show global electricity usage from data centers reaching nearly 945 TWh by 2030, and the Middle East is emerging as a hotspot ...",
      "topic": "Mitsubishi Power",
      "image": "https://gulfbusiness.com/wp-content/uploads/2025/09/Khalid-Salem-president-for-the-Middle-East-North-Africa-at-Mitsubishi-Power.png"
    },
    {
      "id": "dc8534",
      "title": "Mitsubishi Power highlights hydrogen at CERAWeek",
      "link": "http://www.bing.com/news/apiclick.aspx?ref=FexRss&aid=&tid=68e168c5d67846f5821072741e4ab42d&url=https%3a%2f%2fwww.power-eng.com%2fhydrogen%2fmitsubishi-power-highlights-four-hydrogen-projects%2f&c=5094470829493973517&mkt=en-us",
      "date": "Mon, 07 Mar 2022 16:00:00 GMT",
      "summary": "Editor's Note: Clarion Energy's Kevin Clark is on the ground in Houston for CERAWeek and is reporting the latest from the conference. It shouldn\u2019t surprise that hydrogen was a heavily discussed topic ...",
      "topic": "Mitsubishi Power",
      "image": "https://www.power-eng.com/wp-content/uploads/2022/03/newsome2-scaled.jpg"
    },
    {
      "id": "9f317a",
      "title": "Mitsubishi Power Receives 55MW Geothermal Power Plant Order from Pertamina",
      "link": "http://www.bing.com/news/apiclick.aspx?ref=FexRss&aid=&tid=68e168c5d67846f5821072741e4ab42d&url=https%3a%2f%2fwww.nasdaq.com%2fpress-release%2fmitsubishi-power-receives-55mw-geothermal-power-plant-order-from-pertamina-2022-12-05&c=16441117835877105568&mkt=en-us",
      "date": "Sun, 04 Dec 2022 16:25:00 GMT",
      "summary": "TOKYO, Dec 5, 2022 - (JCN Newswire) - - Mitsubishi Power, a power solutions brand of Mitsubishi Heavy Industries, Ltd. (MHI), has received an order from PT Pertamina Geothermal Energy (PGE), the ...",
      "topic": "Mitsubishi Power",
      "image": ""
    },
    {
      "id": "d452ef",
      "title": "Mitsubishi Electric Power Products, Inc. Welcomes New General Manager to its Critical Power Solutions Division",
      "link": "http://www.bing.com/news/apiclick.aspx?ref=FexRss&aid=&tid=68e168c5d67846f5821072741e4ab42d&url=https%3a%2f%2fwww.businesswire.com%2fnews%2fhome%2f20220401005094%2fen%2fMitsubishi-Electric-Power-Products-Inc.-Welcomes-New-General-Manager-to-its-Critical-Power-Solutions-Division&c=15733463736864266715&mkt=en-us",
      "date": "Fri, 01 Apr 2022 05:59:00 GMT",
      "summary": "WARRENDALE, Pa.--(BUSINESS WIRE)--Mitsubishi Electric is pleased to announce John Campion as its new General Manager for the Critical Power Solutions Division (CPSD) of Mitsubishi Electric Power ...",
      "topic": "Mitsubishi Power",
      "image": ""
    },
    {
      "id": "824ba1",
      "title": "Powell Industries: Order Momentum And Backlog Strength Outweigh Top Line Noise",
      "link": "http://www.bing.com/news/apiclick.aspx?ref=FexRss&aid=&tid=68e168d48ea34f3fac392b7a437ecbed&url=https%3a%2f%2fseekingalpha.com%2farticle%2f4827394-powell-industries-stock-order-momentum-backlog-strength-outweigh-top-line-noise&c=2987940541242670654&mkt=en-us",
      "date": "Thu, 02 Oct 2025 02:59:00 GMT",
      "summary": "Powell Industries' Q3'25 report shows strong backlog and diversification for growth. Click here to read more about POWL stock and why it is a Buy.",
      "topic": "Powell substation",
      "image": ""
    },
    {
      "id": "b9bab2",
      "title": "Why Powell Industries (POWL) is a Top Growth Stock for the Long-Term",
      "link": "http://www.bing.com/news/apiclick.aspx?ref=FexRss&aid=&tid=68e168d48ea34f3fac392b7a437ecbed&url=https%3a%2f%2fwww.msn.com%2fen-us%2fmoney%2ftop-stocks%2fwhy-powell-industries-powl-is-a-top-growth-stock-for-the-long-term%2far-AA1NBoze&c=14311904681133262552&mkt=en-us",
      "date": "Tue, 30 Sep 2025 06:45:03 GMT",
      "summary": "For new and old investors, taking full advantage of the stock market and investing with confidence are common goals. Zacks Premium provides lots of different ways to do both. The research service ...",
      "topic": "Powell substation",
      "image": ""
    },
    {
      "id": "a0d8a1",
      "title": "President & CEO Of Powell Industries Purchased $545K In Stock",
      "link": "http://www.bing.com/news/apiclick.aspx?ref=FexRss&aid=&tid=68e168d48ea34f3fac392b7a437ecbed&url=https%3a%2f%2fwww.benzinga.com%2finsights%2fnews%2f25%2f10%2f47996774%2fpresident-ceo-of-powell-industries-purchased-545k-in-stock&c=6949597065821221086&mkt=en-us",
      "date": "Thu, 02 Oct 2025 08:01:00 GMT",
      "summary": "What Happened: In a recent Form 4 filing with the U.S. Securities and Exchange Commission on Wednesday, Cope increased their investment in Powell Industries by purchasing 1,900 shares through ...",
      "topic": "Powell substation",
      "image": "/next-assets/images/benzinga-schema-image-default.png"
    },
    {
      "id": "67bc10",
      "title": "Powell Industries Managing Director Trades $86K In Company Stock",
      "link": "http://www.bing.com/news/apiclick.aspx?ref=FexRss&aid=&tid=68e168d48ea34f3fac392b7a437ecbed&url=https%3a%2f%2fwww.benzinga.com%2finsights%2fnews%2f25%2f10%2f47996761%2fpowell-industries-managing-director-trades-86k-in-company-stock&c=15444718051266565366&mkt=en-us",
      "date": "Thu, 02 Oct 2025 08:01:00 GMT",
      "summary": "What Happened: In a significant move reported in a Form 4 filing with the U.S. Securities and Exchange Commission on Wednesday, Birchall purchased 300 shares of Powell Industries, demonstrating ...",
      "topic": "Powell substation",
      "image": "/next-assets/images/benzinga-schema-image-default.png"
    },
    {
      "id": "21b284",
      "title": "Developed AI for Automatically Detecting Abnormalities in Power Transmission Equipment in Collaboration with Chubu Electric Power Grid Co., Inc.",
      "link": "http://www.bing.com/news/apiclick.aspx?ref=FexRss&aid=&tid=68e168d515874ea8a3f547b1fab38923&url=https%3a%2f%2fwww.suasnews.com%2f2024%2f09%2fdeveloped-ai-for-automatically-detecting-abnormalities-in-power-transmission-equipment-in-collaboration-with-chubu-electric-power-grid-co-inc%2f&c=14040364796663013677&mkt=en-us",
      "date": "Thu, 12 Sep 2024 06:40:00 GMT",
      "summary": "SENSYN ROBOTICS Inc. and Chubu Electric Power Grid Co., Inc. have been jointly developing an AI to automatically detect abnormalities in power transmission facilities.We are pleased to announce that ...",
      "topic": "power transmission equipment shortage",
      "image": ""
    },
    {
      "id": "f18f89",
      "title": "DOE seeks comment on large-scale generation, transmission development",
      "link": "http://www.bing.com/news/apiclick.aspx?ref=FexRss&aid=&tid=68e168d515874ea8a3f547b1fab38923&url=https%3a%2f%2fwww.yahoo.com%2fnews%2farticles%2fdoe-seeks-large-scale-generation-145625122.html&c=7788146563721296676&mkt=en-us",
      "date": "Thu, 18 Sep 2025 07:56:00 GMT",
      "summary": "The \u201cSpeed to Power\u201d initiative could boost grid reliability and affordability, but only if all energy resources are included, said John Moore, director of the Sustainable FERC Project.",
      "topic": "power transmission equipment shortage",
      "image": "https://s.yimg.com/ny/api/res/1.2/M0_aqbgQp5ZIGO_p1HftHQ--/YXBwaWQ9aGlnaGxhbmRlcjt3PTEyMDA7aD02NzU7Y2Y9d2VicA--/https://media.zenfs.com/en/utility_dive_591/3a41b3215db0d72139c003e9377ccd3f"
    },
    {
      "id": "8e8c73",
      "title": "Oregon passes bills to bolster electric grid amid \u2018alarming\u2019 transmission shortage",
      "link": "http://www.bing.com/news/apiclick.aspx?ref=FexRss&aid=&tid=68e168d515874ea8a3f547b1fab38923&url=https%3a%2f%2fwww.yahoo.com%2fnews%2foregon-passes-bills-bolster-electric-193118943.html&c=17931996155559295376&mkt=en-us",
      "date": "Thu, 19 Jun 2025 12:31:00 GMT",
      "summary": "PORTLAND, Ore. (KOIN) \u2013 The Oregon legislature passed two bills this session aiming to strengthen the electric grid amid an \u201calarming\u201d shortage of electrical transmission capacity across the state, ...",
      "topic": "power transmission equipment shortage",
      "image": "https://media.zenfs.com/en/koin_articles_940/5b702fd275bb48249dd8eec455f9b134"
    },
    {
      "id": "b49f68",
      "title": "American Transmission vies for piece of $3.8B in Wisconsin power-grid projects",
      "link": "http://www.bing.com/news/apiclick.aspx?ref=FexRss&aid=&tid=68e168d515874ea8a3f547b1fab38923&url=https%3a%2f%2fwww.bizjournals.com%2fmilwaukee%2fnews%2f2024%2f12%2f24%2fwisconsin-set-to-join-power-grid-super-highway.html&c=3636097499121852901&mkt=en-us",
      "date": "Mon, 23 Dec 2024 16:00:00 GMT",
      "summary": "With burgeoning electricity uses that increasingly stress the power grid \u2014 including data centers and electric vehicles \u2014 Wisconsin\u2019s transmission lines could get a boost through an estimated $3.8 ...",
      "topic": "power transmission equipment shortage",
      "image": ""
    },
    {
      "id": "b49191",
      "title": "China's data center power supply outpaces US amid growing AI demand",
      "link": "http://www.bing.com/news/apiclick.aspx?ref=FexRss&aid=&tid=68e168d515874ea8a3f547b1fab38923&url=https%3a%2f%2fwww.digitimes.com%2fnews%2fa20250821PD206%2finfrastructure-demand-power-supply-data-center-electricity.html&c=8469018782876980987&mkt=en-us",
      "date": "Sat, 23 Aug 2025 17:00:00 GMT",
      "summary": "As artificial intelligence infrastructure expands worldwide, China has effectively addressed power supply challenges for its data centers, while the US continues to face grid limitations, equipment ...",
      "topic": "power transmission equipment shortage",
      "image": "https://img.digitimes.com/newsshow/20250821pd206_files/1_b.jpg"
    },
    {
      "id": "809225",
      "title": "Myanmar says rebel attacks, gas shortages worsen power crisis",
      "link": "http://www.bing.com/news/apiclick.aspx?ref=FexRss&aid=&tid=68e168d515874ea8a3f547b1fab38923&url=https%3a%2f%2fwww.reuters.com%2fworld%2fasia-pacific%2fmyanmar-says-rebel-attacks-gas-shortages-worsen-power-crisis-2025-01-17%2f&c=12982764129622253859&mkt=en-us",
      "date": "Fri, 17 Jan 2025 01:54:00 GMT",
      "summary": "Output down to about half of typical daily figure of 4,000 MW Rebel attacks on transmission lines cripple capacity, junta says Power cuts worsen in commercial centre of Yangon Junta has ruled since ...",
      "topic": "power transmission equipment shortage",
      "image": ""
    },
    {
      "id": "0f7e94",
      "title": "Federal agency finding clears path for construction to begin on divisive LANL power transmission line",
      "link": "http://www.bing.com/news/apiclick.aspx?ref=FexRss&aid=&tid=68e168d515874ea8a3f547b1fab38923&url=https%3a%2f%2fwww.santafenewmexican.com%2fnews%2flocal_news%2ffederal-agency-finding-clears-path-for-construction-to-begin-on-divisive-lanl-power-transmission-line%2farticle_17f71416-d5c1-4640-b971-c55bd15395bc.html&c=2917061896977249493&mkt=en-us",
      "date": "Mon, 11 Aug 2025 17:00:00 GMT",
      "summary": "The National Nuclear Security Administration has issued a finding of \u201cno significant impact\u201d for a proposed 14-mile, 115-kilovolt transmission line to service Los Alamos National Laboratory and Los ...",
      "topic": "power transmission equipment shortage",
      "image": "https://bloximages.newyork1.vip.townnews.com/santafenewmexican.com/content/tncms/assets/v3/editorial/4/7d/47d49ef6-693a-45ff-a08e-4fc76036a6de/64d80c2f2e259.image.png?crop=1952%2C1025%2C0%2C18&resize=1200%2C630&order=crop%2Cresize"
    },
    {
      "id": "2e6643",
      "title": "Mon Power to Replace and Upgrade Equipment at Eight Transmission Substations",
      "link": "http://www.bing.com/news/apiclick.aspx?ref=FexRss&aid=&tid=68e168d515874ea8a3f547b1fab38923&url=https%3a%2f%2fwww.tdworld.com%2fsubstations%2fnews%2f55135349%2ffirstenergys-mon-power-to-replace-and-upgrade-equipment-at-eight-transmission-substations-in-west-virginia&c=3820205305386006615&mkt=en-us",
      "date": "Thu, 22 Aug 2024 16:59:00 GMT",
      "summary": "FirstEnergy electric company Mon Power is replacing and upgrading equipment at eight transmission substations in its West Virginia service territory to help prevent or minimize the impact of power ...",
      "topic": "power transmission equipment shortage",
      "image": "https://img.tdworld.com/files/base/ebm/tdworld/image/2024/08/66c89ed19346142f3a86d266-24630282235_bcc5be373c_k.png?auto=format,compress&fit=fill&fill=blur&w=1200&h=630"
    },
    {
      "id": "331b12",
      "title": "Retrofit or replace? How utilities are evaluating transformer life extension",
      "link": "http://www.bing.com/news/apiclick.aspx?ref=FexRss&aid=&tid=68e168d9f0a24ba99d20cb13688af42d&url=https%3a%2f%2fwww.renewableenergyworld.com%2fpower-grid%2fretrofit-or-replace-how-utilities-are-evaluating-transformer-life-extension%2f&c=16468289516933828354&mkt=en-us",
      "date": "Thu, 02 Oct 2025 18:00:00 GMT",
      "summary": "This Reinhausen and Factor This webinar contains strategic insights into OLTC retrofit decision frameworks being implemented by utilities.",
      "topic": "transformer lead time extension",
      "image": "https://www.renewableenergyworld.com/wp-content/uploads/2025/10/FT-Template-27.jpg"
    },
    {
      "id": "fa84b8",
      "title": "The Transformer Crisis: An Industry on the Brink",
      "link": "http://www.bing.com/news/apiclick.aspx?ref=FexRss&aid=&tid=68e168d9f0a24ba99d20cb13688af42d&url=https%3a%2f%2fwww.powermag.com%2fthe-transformer-crisis-an-industry-on-the-brink%2f&c=18161894940950096048&mkt=en-us",
      "date": "Tue, 25 Jun 2024 17:00:00 GMT",
      "summary": "Facing unprecedented lead times and skyrocketing costs, the transformer supply chain crisis threatens the backbone of the electric power industry, driving urgent calls for increased manufacturing ...",
      "topic": "transformer lead time extension",
      "image": "https://www.powermag.com/wp-content/uploads/2024/06/fig4-flexible-transformer-cooperative-energy.jpeg"
    },
    {
      "id": "c8e70b",
      "title": "High Voltage: Lithium prices jump, but supply chain scares in Chile and China may just be a hiccup",
      "link": "http://www.bing.com/news/apiclick.aspx?ref=FexRss&aid=&tid=68e168da6c7247479c1e8687d849fdf4&url=https%3a%2f%2fwww.msn.com%2fen-au%2fmoney%2fmarkets%2fhigh-voltage-lithium-prices-jump-but-supply-chain-scares-in-chile-and-china-may-just-be-a-hiccup%2far-AA1KyswV&c=4886337798761716742&mkt=en-us",
      "date": "Thu, 14 Aug 2025 19:47:00 GMT",
      "summary": "Our High Voltage column wraps all the news driving ASX stocks with exposure to lithium, cobalt, graphite, nickel, rare earths, and vanadium. Frailties in the lithium supply chain have been put on ...",
      "topic": "high voltage cable supply chain",
      "image": ""
    },
    {
      "id": "2a5225",
      "title": "Aesen, DOC JV Targets Subsea Cable Logistics",
      "link": "http://www.bing.com/news/apiclick.aspx?ref=FexRss&aid=&tid=68e168da6c7247479c1e8687d849fdf4&url=https%3a%2f%2fwww.marinelink.com%2fnews%2faesen-doc-jv-targets-subsea-cable-530525&c=9559789292272576248&mkt=en-us",
      "date": "Mon, 29 Sep 2025 08:25:00 GMT",
      "summary": "Aesen Pte. Ltd. (Aesen) and Dutch Offshore Contractors Holdings B.V. (DOC) \u00a0formed Aesen DOC Cable Logistics Pte. Ltd., a joint ...",
      "topic": "high voltage cable supply chain",
      "image": "https://images.marinelink.com/images/maritime/w800/image-courtesy-164112.jpg"
    },
    {
      "id": "dee9e1",
      "title": "Taihan begins construction on second submarine cable plant",
      "link": "http://www.bing.com/news/apiclick.aspx?ref=FexRss&aid=&tid=68e168da6c7247479c1e8687d849fdf4&url=https%3a%2f%2fwww.4coffshore.com%2fnews%2ftaihan-begins-construction-on-second-submarine-cable-plant-nid31889.html&c=12003737801834787073&mkt=en-us",
      "date": "Fri, 26 Sep 2025 01:07:00 GMT",
      "summary": "South Korea's Taihan has begun construction on its second submarine cable plant in Dangjin. Designed to manufacture 640kV-class HVDC and 400kV-class HVAC cables, the facility is being built next to ...",
      "topic": "high voltage cable supply chain",
      "image": ""
    },
    {
      "id": "9e02c9",
      "title": "$387.3 Bn Wire and Cables Materials, Technologies and Global Markets to 2029 with Infrastructure Developments and Renewable Energy Fueling Growth - ResearchAndMarkets.com",
      "link": "http://www.bing.com/news/apiclick.aspx?ref=FexRss&aid=&tid=68e168da6c7247479c1e8687d849fdf4&url=https%3a%2f%2fwww.businesswire.com%2fnews%2fhome%2f20241104646146%2fen%2f&c=15723455379265809630&mkt=en-us",
      "date": "Mon, 04 Nov 2024 01:00:00 GMT",
      "summary": "DUBLIN--(BUSINESS WIRE)--The \"Wire and Cables: Materials, Technologies and Global Markets\" report has been added to ResearchAndMarkets.com's offering. The global market for wire and cable is expected ...",
      "topic": "high voltage cable supply chain",
      "image": ""
    },
    {
      "id": "039e97",
      "title": "Trump administration rejects \u2018net-zero\u2019 plan and carbon tax for international shipping",
      "link": "http://www.bing.com/news/apiclick.aspx?ref=FexRss&aid=&tid=68e168dbf0454e388e39d4c241d93fb4&url=https%3a%2f%2fwww.washingtonexaminer.com%2fpolicy%2fenergy-and-environment%2f3497893%2fus-rejects-shipping-carbon-tax%2f&c=15888575092178074387&mkt=en-us",
      "date": "Tue, 12 Aug 2025 09:28:00 GMT",
      "summary": "\u201cWhatever its stated goals, the proposed framework is effectively a global carbon tax on Americans levied by an unaccountable UN organization,\u201d the statement read. The secretaries claimed that the ...",
      "topic": "international shipping costs energy",
      "image": "https://www.washingtonexaminer.com/wp-content/uploads/2025/02/AP25036684411248-scaled.webp?resize=1024,683"
    },
    {
      "id": "49e0ed",
      "title": "LNG demand for ships set to at least double by 2030 globally",
      "link": "http://www.bing.com/news/apiclick.aspx?ref=FexRss&aid=&tid=68e168dbf0454e388e39d4c241d93fb4&url=https%3a%2f%2fwww.reuters.com%2fbusiness%2fenergy%2flng-demand-ships-set-least-double-by-2030-globally-2025-10-02%2f&c=7431959567419543545&mkt=en-us",
      "date": "Thu, 02 Oct 2025 06:47:00 GMT",
      "summary": "Demand for liquefied natural gas as a marine fuel will at least double by 2030 as abundant supply and rising emissions regulations spur orders for ships that can run on it, industry executives said.",
      "topic": "international shipping costs energy",
      "image": ""
    },
    {
      "id": "ec04af",
      "title": "Andrea Dos Santos's International Energy Expertise: Drives Sustainable Fuel Solutions for Hard-to-Electrify Sectors",
      "link": "http://www.bing.com/news/apiclick.aspx?ref=FexRss&aid=&tid=68e168dbf0454e388e39d4c241d93fb4&url=https%3a%2f%2fwww.msn.com%2fen-us%2fmoney%2fcompanies%2fandrea-dos-santos-s-international-energy-expertise-drives-sustainable-fuel-solutions-for-hard-to-electrify-sectors%2far-AA1KxU4m&c=18207395302792854685&mkt=en-us",
      "date": "Fri, 05 Sep 2025 12:09:00 GMT",
      "summary": "Cross-cultural biofuel consulting experience shapes sustainable fuel transitions for aviation, shipping, and heavy transport sectors While electric cars dominate headlines, many industries can\u2019t ...",
      "topic": "international shipping costs energy",
      "image": ""
    },
    {
      "id": "9f2822",
      "title": "Editorial: Biofuels global shipping energy demand by 2030?",
      "link": "http://www.bing.com/news/apiclick.aspx?ref=FexRss&aid=&tid=68e168dbf0454e388e39d4c241d93fb4&url=https%3a%2f%2fwww.msn.com%2fen-xl%2fmoney%2ftopstories%2feditorial-biofuels-global-shipping-energy-demand-by-2030%2far-AA1CrZSX&c=1508743174353663215&mkt=en-us",
      "date": "Mon, 07 Apr 2025 06:16:00 GMT",
      "summary": "The push for biofuels in international shipping has been shot down by a coalition of climate-focused organisations, who warn that its adoption under new climate measures could exacerbate food ...",
      "topic": "international shipping costs energy",
      "image": ""
    },
    {
      "id": "89a28d",
      "title": "Estimating the maximum potential vegetable oil demand for international shipping under the International Maritime Organization\u2019s Net-Zero Framework",
      "link": "http://www.bing.com/news/apiclick.aspx?ref=FexRss&aid=&tid=68e168dbf0454e388e39d4c241d93fb4&url=https%3a%2f%2ftheicct.org%2fpublication%2festimating-the-maximum-potential-vegetable-oil-demand-for-international-shipping-under-the-imo-net-zero-framework-sept25%2f&c=8147822012767893157&mkt=en-us",
      "date": "Fri, 26 Sep 2025 12:34:00 GMT",
      "summary": "This brief highlights how IMO\u2019s Net-Zero Framework could incentivize the use of vegetable oil-based biofuels and estimates the potential demand for vegetable oils.",
      "topic": "international shipping costs energy",
      "image": "https://theicct.org/wp-content/uploads/2025/09/AdobeStock_317012409-scaled.jpeg"
    },
    {
      "id": "49a14a",
      "title": "Shipping companies support a first-ever global fee on greenhouse gases, opposed by Trump officials",
      "link": "http://www.bing.com/news/apiclick.aspx?ref=FexRss&aid=&tid=68e168dbf0454e388e39d4c241d93fb4&url=https%3a%2f%2fwww.ocregister.com%2f2025%2f09%2f15%2fclimate-international-shipping-fee%2f&c=12230560024511849826&mkt=en-us",
      "date": "Mon, 15 Sep 2025 16:15:00 GMT",
      "summary": "Nearly 200 shipping companies said Monday they want the world\u2019s largest maritime nations to adopt regulations that include the first-ever global fee on greenhouse gases to reduce their sector\u2019s ...",
      "topic": "international shipping costs energy",
      "image": "https://www.ocregister.com/wp-content/uploads/2025/09/Climate_International_Shipping_76919-1.jpg?w=1024&h=682"
    },
    {
      "id": "3fa6d2",
      "title": "LNG Shipping Costs Soar to 8-Month High Amid Middle East Turmoil",
      "link": "http://www.bing.com/news/apiclick.aspx?ref=FexRss&aid=&tid=68e168dbf0454e388e39d4c241d93fb4&url=https%3a%2f%2foilprice.com%2fLatest-Energy-News%2fWorld-News%2fLNG-Shipping-Costs-Soar-to-8-Month-High-Amid-Middle-East-Turmoil.html&c=14048812990533439579&mkt=en-us",
      "date": "Tue, 24 Jun 2025 03:00:00 GMT",
      "summary": "LNG shipping costs have surged to the highest in eight months as shipowners assess Middle East risks and hold off chartering vessels, reducing available ships, while price signals in Asia are favoring ...",
      "topic": "international shipping costs energy",
      "image": "https://d1o9e4un86hhpc.cloudfront.net/images/facebook-share-logo.png"
    },
    {
      "id": "c9a8e2",
      "title": "One unintended result from the trade war? Shipping costs have doubled.",
      "link": "http://www.bing.com/news/apiclick.aspx?ref=FexRss&aid=&tid=68e168dbf0454e388e39d4c241d93fb4&url=https%3a%2f%2fwww.marketplace.org%2fstory%2f2025%2f06%2f13%2fshipping-costs-have-doubled-thanks-to-trumps-trade-war&c=17191737912930191086&mkt=en-us",
      "date": "Thu, 12 Jun 2025 19:00:00 GMT",
      "summary": "Shipping companies rerouted their ships from China when tariffs were over 100%, and now it will take a while to get them back down. The Trump administration\u2019s on-again, off-again approach to trade ...",
      "topic": "international shipping costs energy",
      "image": "https://img.apmcdn.org/317a8216bd77cc15def61905797b1af4909cb3a9/widescreen/1db3ae-20250613-aerial-view-of-shipping-containers-stacked-at-a-port-in-shanghai-2000.jpg"
    },
    {
      "id": "45f707",
      "title": "Shipping companies support a first-ever global fee on greenhouse gases, opposed by Trump officials",
      "link": "http://www.bing.com/news/apiclick.aspx?ref=FexRss&aid=&tid=68e168dbf0454e388e39d4c241d93fb4&url=https%3a%2f%2fwinknews.com%2fnews%2finternational%2fshipping-companies-support-a-first-ever-global-fee-on-greenhouse-gases-opposed-by-trump-officials%2farticle_c7c9075b-828f-51ac-b3b7-f22b69eab7d5.html&c=1861956429465544010&mkt=en-us",
      "date": "Sun, 14 Sep 2025 17:00:00 GMT",
      "summary": "Nearly 200 shipping companies said Monday they want the world\u2019s largest maritime nations to adopt regulations that include the first-ever global fee on greenhouse gases to reduce their sector\u2019s ...",
      "topic": "international shipping costs energy",
      "image": "https://bloximages.chicago2.vip.townnews.com/winknews.com/content/tncms/custom/image/2c126f9c-bedd-11ef-8535-37037507a88a.png?resize=600%2C315"
    },
    {
      "id": "354ef3",
      "title": "Virar: 12-year delay hits high voltage substation project; plot ownership still with state",
      "link": "http://www.bing.com/news/apiclick.aspx?ref=FexRss&aid=&tid=68e168de48484174af0c3eb498f6a66c&url=https%3a%2f%2fwww.msn.com%2fen-in%2fpolitics%2fgovernment%2fvirar-12-year-delay-hits-high-voltage-substation-project-plot-ownership-still-with-state%2far-AA1MRWCS&c=9965182693922181500&mkt=en-us",
      "date": "Thu, 18 Sep 2025 21:43:00 GMT",
      "summary": "The MSETCL's planned EHV substation in Virar West faces significant delays, with ownership of the allocated plot still pending after five years. This hold-up, despite initiated tender processes, has ...",
      "topic": "HV substation project delay",
      "image": ""
    },
    {
      "id": "5c765e",
      "title": "Intel delays leave new AEP substation with nothing to power",
      "link": "http://www.bing.com/news/apiclick.aspx?ref=FexRss&aid=&tid=68e168de48484174af0c3eb498f6a66c&url=https%3a%2f%2fwww.dispatch.com%2fstory%2fnews%2f2025%2f06%2f12%2fintel-chip-factory-aep-ohio-substation%2f84150713007%2f&c=10625332334822076499&mkt=en-us",
      "date": "Wed, 11 Jun 2025 17:00:00 GMT",
      "summary": "AEP Ohio's new substation will be finished in August, but Intel's chip factory delays mean it will initially lack a power consumer. Intel's financial troubles have pushed the factory opening to 2030 ...",
      "topic": "HV substation project delay",
      "image": "https://www.dispatch.com/gcdn/authoring/authoring-images/2025/04/23/NCOD/83233088007-presto-image-74635944007.jpg?crop=4799,2699,x0,y0&width=3200&height=1800&format=pjpg&auto=webp"
    },
    {
      "id": "169ae5",
      "title": "Transformer damage causes further delay in West Lake rail project",
      "link": "http://www.bing.com/news/apiclick.aspx?ref=FexRss&aid=&tid=68e168de48484174af0c3eb498f6a66c&url=https%3a%2f%2fwww.nwitimes.com%2fnews%2flocal%2farticle_e5f52ef9-fb17-49cb-b5ec-14471569f884.html&c=6337338598880355487&mkt=en-us",
      "date": "Mon, 29 Sep 2025 13:30:00 GMT",
      "summary": "The South Shore Line\u2019s West Lake Corridor project encountered another hurdle when two of the transformers that would send power to the new rail line were damaged during an electrical storm in August.",
      "topic": "HV substation project delay",
      "image": "https://bloximages.chicago2.vip.townnews.com/nwitimes.com/content/tncms/assets/v3/editorial/e/5f/e5f52ef9-fb17-49cb-b5ec-14471569f884/68dae48030dcb.preview.jpg?crop=1763%2C926%2C0%2C124&resize=1200%2C630&order=crop%2Cresize"
    },
    {
      "id": "e10fdc",
      "title": "IN: Transformer damage causes further delay in West Lake rail project",
      "link": "http://www.bing.com/news/apiclick.aspx?ref=FexRss&aid=&tid=68e168de48484174af0c3eb498f6a66c&url=https%3a%2f%2fwww.masstransitmag.com%2frail%2finfrastructure%2fnews%2f55320294%2fin-transformer-damage-causes-further-delay-in-west-lake-rail-project&c=5832261606107764417&mkt=en-us",
      "date": "Wed, 01 Oct 2025 02:15:00 GMT",
      "summary": "The South Shore Line\u2019s West Lake Corridor project encountered another hurdle when two of the transformers that would send power to the new rail line were damaged during an ...",
      "topic": "HV substation project delay",
      "image": "https://img.masstransitmag.com/files/base/cygnus/mass/image/static/logo/site_logo.png?auto=format,compress&fit=fill&fill=solid&fill-color=&w=1200&h=627"
    }
  ]
}